{
    "production": false,
    "authentication": false,
    "auth": {
        "host": "xxx",
        "token": "xxx",
        "email": "xxx@xxx.co.za",
        "appId": "xxx"
    },
    "logger": {
        "appenders": {
            "docs": {
                "type": "file",
                "backups": 10,
                "filename": "./logs/docs.log",
                "absolute": true,
                "maxLogSize": 102400
            }
        },
        "categories": {
            "default": {
                "appenders": [
                    "docs"
                ],
                "level": "error"
            }
        }
    },
    "mongodb": {
        "url": "xxx",
        "database": "xxx"
    },
    "localwebserver": {
        "port": 15000
    }
}